LICENSE.md
README.md
setup.cfg
setup.py
jenganizer/__init__.py
jenganizer/jenganizer.py
jenganizer.egg-info/PKG-INFO
jenganizer.egg-info/SOURCES.txt
jenganizer.egg-info/dependency_links.txt
jenganizer.egg-info/entry_points.txt
jenganizer.egg-info/requires.txt
jenganizer.egg-info/top_level.txt