Metadata-Version: 2.1
Name: jenganizer
Version: 0.1.1
Summary: Jenganizer is a tool to map hidden services in AWS. It does this by following the triggered events of a user's actions. When a user performs an action in AWS, it can trigger other events in other services. By following these events, users can identify services that are indirectly deployed by their actions. This can be important, as these resources can present security risks which should be managed and controlled.
Home-page: https://github.com/tenable/hidden-services-revealer
Author: Tenable Inc.
Author-email: cs.research+opensource@tenable.com
Project-URL: Bug Tracker, https://github.com/tenable/hidden-services-revealer/issues
Classifier: Programming Language :: Python :: 3
Classifier: License :: OSI Approved :: Apache Software License
Classifier: Operating System :: OS Independent
Requires-Python: >=3.8
License-File: LICENSE.md
Requires-Dist: boto3
Requires-Dist: click
Requires-Dist: click-log
Requires-Dist: colorlog
